Workbook
Name Slicer_CustomerType1: #N/A
Name Slicer_CustomerType2: #N/A
Name Slicer_PaymentMethod: #N/A
Name Slicer_Product: #N/A
Name Slicer_Region: #N/A
Name Slicer_RegionManager: #N/A
Name Slicer_Years__OrderDate: #N/A

Sheet Sheet2
A3: Row Labels | B3: Sum of Net Sales | C3: Sum of Profit | E3: Sales vc PY | F3: Sales vc PY
A4: 2023 | B4: 1697870 | C4: -132848.99
A5: 2024 | B5: 1771954.8 | C5: -140330.63 | E5: =B5/B4-1 -> 0.043633968 | F5: =C5/C4-1 -> 0.056316847
A6: 2025 | B6: 910167.67 | C6: -74720.888
A7: Grand Total | B7: 4379992.4 | C7: -347900.51
A9: Sale

Sheet Sheet3
A1: Table 1&2
A3: Sum of Net Sales | B3: Column Labels | G3: Sum of Net Sales | H3: Column Labels
B4: 2023 | C4: 2024 | H4: 2023 | I4: 2024
A7: Row Labels | G7: Row Labels
A8: Tablet | B8: 268581.74 | C8: 297185.16 | G8: Central | H8: 317187.37 | I8: 316403.47
A9: Monitor | B9: 252496.86 | C9: 294518.33 | G9: East | H9: 311347.12 | I9: 361402.37
A10: Laptop | B10: 286177.2 | C10: 256697.07 | G10: North | H10: 360780.62 | I10: 377736.99
A11: Printer | B11: 222621.63 | C11: 319790.82 | G11: South | H11: 330323.74 | I11: 382472.17
A12: Chair | B12: 205814.54 | C12: 248450.11 | G12: West | H12: 378231.13 | I12: 333939.79
A13: Desk | B13: 257695.83 | C13: 185283.95 | G13: Grand Total | H13: 1697870 | I13: 1771954.8
A14: Phone | B14: 204482.17 | C14: 170029.35
A15: Grand Total | B15: 1697870 | C15: 1771954.8
A18: Table 3& 4
A20: Sum of Net Sales | B20: Column Labels | G20: Sum of Net Sales | H20: Column Labels
B21: 2023 | C21: 2024 | H21: 2023 | I21: 2024
A24: Row Labels | G24: Row Labels
A25: Tablet | B25: 268581.74 | C25: 297185.16 | G25: Central | H25: 317187.37 | I25: 316403.47
A26: Monitor | B26: 252496.86 | C26: 294518.33 | G26: East | H26: 311347.12 | I26: 361402.37
A27: Laptop | B27: 286177.2 | C27: 256697.07 | G27: North | H27: 360780.62 | I27: 377736.99
A28: Printer | B28: 222621.63 | C28: 319790.82 | G28: South | H28: 330323.74 | I28: 382472.17
A29: Chair | B29: 205814.54 | C29: 248450.11 | G29: West | H29: 378231.13 | I29: 333939.79
A30: Desk | B30: 257695.83 | C30: 185283.95 | G30: Grand Total | H30: 1697870 | I30: 1771954.8
A31: Phone | B31: 204482.17 | C31: 170029.35
A32: Grand Total | B32: 1697870 | C32: 1771954.8

Sheet Sheet4
A3: Years (OrderDate) | B3: Quarters (OrderDate) | C3: Sum of Net Sales | D3: Sum of Quantity | H3: Sales | I3: Price
A4: 2023 | B4: Qtr1 | C4: 502717.8 | D4: 1753 | F4: =A4 -> 2023 | G4: =B4 -> Qtr1 | H4: =C4 -> 502717.8 | I4: =H4/D4 -> 286.7757
B5: Qtr2 | C5: 400622.36 | D5: 1343 | G5: =B5 -> Qtr2 | H5: =C5 -> 400622.36 | I5: =H5/D5 -> 298.30407
B6: Qtr3 | C6: 451217.88 | D6: 1608 | G6: =B6 -> Qtr3 | H6: =C6 -> 451217.88 | I6: =H6/D6 -> 280.60814
B7: Qtr4 | C7: 343311.94 | D7: 1350 | G7: =B7 -> Qtr4 | H7: =C7 -> 343311.94 | I7: =H7/D7 -> 254.30514
A8: 2024 | B8: Qtr1 | C8: 450312.98 | D8: 1618 | F8: =A8 -> 2024 | G8: =B8 -> Qtr1 | H8: =C8 -> 450312.98 | I8: =H8/D8 -> 278.31457
B9: Qtr2 | C9: 461674.88 | D9: 1549 | G9: =B9 -> Qtr2 | H9: =C9 -> 461674.88 | I9: =H9/D9 -> 298.04705
B10: Qtr3 | C10: 400585.82 | D10: 1460 | G10: =B10 -> Qtr3 | H10: =C10 -> 400585.82 | I10: =H10/D10 -> 274.37385
B11: Qtr4 | C11: 459381.1 | D11: 1588 | G11: =B11 -> Qtr4 | H11: =C11 -> 459381.1 | I11: =H11/D11 -> 289.28281
A12: 2025 | B12: Qtr1 | C12: 492476.49 | D12: 1844 | F12: =A12 -> 2025 | G12: =B12 -> Qtr1 | H12: =C12 -> 492476.49 | I12: =H12/D12 -> 267.06968
B13: Qtr2 | C13: 417691.18 | D13: 1503 | G13: =B13 -> Qtr2 | H13: =C13 -> 417691.18 | I13: =H13/D13 -> 277.90497
A14: Grand Total | C14: 4379992.4 | D14: 15616
A39: Region | B39: Sum of Net Sales | C39: Sum of Quantity | E39: Region | F39: Sales
A40: North | B40: 967957.98 | C40: 3442 | E40: =A40 -> North | F40: =B40 -> 967957.98
A41: East | B41: 883633.72 | C41: 3078 | E41: =A41 -> East | F41: =B41 -> 883633.72
A42: West | B42: 853478.86 | C42: 3041 | E42: =A42 -> West | F42: =B42 -> 853478.86
A43: Central | B43: 847153.68 | C43: 3102 | E43: =A43 -> Central | F43: =B43 -> 847153.68
A44: South | B44: 827768.19 | C44: 2953 | E44: =A44 -> South | F44: =B44 -> 827768.19
A45: Grand Total | B45: 4379992.4 | C45: 15616

Sheet Sheet5
B16: Product | D16: 2023 | E16: 2024 | F16: vs PY | H16: Region | J16: 2023 | K16: 2024 | L16: vs PY | N16: Product | P16: 2023 | Q16: 2024 | R16: vs PY | T16: Region | V16: 2023 | W16: 2024 | X16: vs PY
B17: =Sheet3!A8 -> Tablet | D17: =Sheet3!B8 -> 268581.74 | E17: =Sheet3!C8 -> 297185.16 | F17: =D17/E17-1 -> -0.096247817 | H17: =Sheet3!G8 -> Central | J17: =Sheet3!H8 -> 317187.37 | K17: =Sheet3!I8 -> 316403.47 | L17: =J17/K17-1 -> 0.0024775456 | N17: =Sheet3!A25 -> Tablet | P17: =Sheet3!B25 -> 268581.74 | Q17: =Sheet3!C25 -> 297185.16 | R17: =P17/Q17-1 -> -0.096247817 | T17: =Sheet3!G25 -> Central | V17: =Sheet3!H25 -> 317187.37 | W17: =Sheet3!I25 -> 316403.47 | X17: =V17/W17-1 -> 0.0024775456
B18: =Sheet3!A9 -> Monitor | D18: =Sheet3!B9 -> 252496.86 | E18: =Sheet3!C9 -> 294518.33 | F18: =D18/E18-1 -> -0.1426786 | H18: =Sheet3!G9 -> East | J18: =Sheet3!H9 -> 311347.12 | K18: =Sheet3!I9 -> 361402.37 | L18: =J18/K18-1 -> -0.13850283 | N18: =Sheet3!A26 -> Monitor | P18: =Sheet3!B26 -> 252496.86 | Q18: =Sheet3!C26 -> 294518.33 | R18: =P18/Q18-1 -> -0.1426786 | T18: =Sheet3!G26 -> East | V18: =Sheet3!H26 -> 311347.12 | W18: =Sheet3!I26 -> 361402.37 | X18: =V18/W18-1 -> -0.13850283
B19: =Sheet3!A10 -> Laptop | D19: =Sheet3!B10 -> 286177.2 | E19: =Sheet3!C10 -> 256697.07 | F19: =D19/E19-1 -> 0.11484406 | H19: =Sheet3!G10 -> North | J19: =Sheet3!H10 -> 360780.62 | K19: =Sheet3!I10 -> 377736.99 | L19: =J19/K19-1 -> -0.044889345 | N19: =Sheet3!A27 -> Laptop | P19: =Sheet3!B27 -> 286177.2 | Q19: =Sheet3!C27 -> 256697.07 | R19: =P19/Q19-1 -> 0.11484406 | T19: =Sheet3!G27 -> North | V19: =Sheet3!H27 -> 360780.62 | W19: =Sheet3!I27 -> 377736.99 | X19: =V19/W19-1 -> -0.044889345
B20: =Sheet3!A11 -> Printer | D20: =Sheet3!B11 -> 222621.63 | E20: =Sheet3!C11 -> 319790.82 | F20: =D20/E20-1 -> -0.30385235 | H20: =Sheet3!G11 -> South | J20: =Sheet3!H11 -> 330323.74 | K20: =Sheet3!I11 -> 382472.17 | L20: =J20/K20-1 -> -0.13634568 | N20: =Sheet3!A28 -> Printer | P20: =Sheet3!B28 -> 222621.63 | Q20: =Sheet3!C28 -> 319790.82 | R20: =P20/Q20-1 -> -0.30385235 | T20: =Sheet3!G28 -> South | V20: =Sheet3!H28 -> 330323.74 | W20: =Sheet3!I28 -> 382472.17 | X20: =V20/W20-1 -> -0.13634568
B21: =Sheet3!A12 -> Chair | D21: =Sheet3!B12 -> 205814.54 | E21: =Sheet3!C12 -> 248450.11 | F21: =D21/E21-1 -> -0.17160613 | H21: =Sheet3!G12 -> West | J21: =Sheet3!H12 -> 378231.13 | K21: =Sheet3!I12 -> 333939.79 | L21: =J21/K21-1 -> 0.13263271 | N21: =Sheet3!A29 -> Chair | P21: =Sheet3!B29 -> 205814.54 | Q21: =Sheet3!C29 -> 248450.11 | R21: =P21/Q21-1 -> -0.17160613 | T21: =Sheet3!G29 -> West | V21: =Sheet3!H29 -> 378231.13 | W21: =Sheet3!I29 -> 333939.79 | X21: =V21/W21-1 -> 0.13263271
B22: =Sheet3!A13 -> Desk | D22: =Sheet3!B13 -> 257695.83 | E22: =Sheet3!C13 -> 185283.95 | F22: =D22/E22-1 -> 0.39081574 | H22: Total | J22: =Sheet3!H13 -> 1697870 | K22: =Sheet3!I13 -> 1771954.8 | L22: =J22/K22-1 -> -0.041809647 | N22: =Sheet3!A30 -> Desk | P22: =Sheet3!B30 -> 257695.83 | Q22: =Sheet3!C30 -> 185283.95 | R22: =P22/Q22-1 -> 0.39081574 | T22: Total | V22: =Sheet3!H30 -> 1697870 | W22: =Sheet3!I30 -> 1771954.8 | X22: =V22/W22-1 -> -0.041809647
B23: =Sheet3!A14 -> Phone | D23: =Sheet3!B14 -> 204482.17 | E23: =Sheet3!C14 -> 170029.35 | F23: =D23/E23-1 -> 0.20262869 | N23: =Sheet3!A31 -> Phone | P23: =Sheet3!B31 -> 204482.17 | Q23: =Sheet3!C31 -> 170029.35 | R23: =P23/Q23-1 -> 0.20262869
B24: Total | D24: =Sheet3!B15 -> 1697870 | E24: =Sheet3!C15 -> 1771954.8 | F24: =D24/E24-1 -> -0.041809647 | N24: Total | P24: =Sheet3!B32 -> 1697870 | Q24: =Sheet3!C32 -> 1771954.8 | R24: =P24/Q24-1 -> -0.041809647

Sheet Sheet1
A1: Date | B1: Region | C1: Product | D1: Quantity | E1: UnitPrice | F1: StoreLocation | G1: CustomerType | H1: Discount | I1: Salesperson | J1: TotalPrice | K1: PaymentMethod | L1: Promotion | M1: Returned | N1: OrderID | O1: CustomerName | P1: ShippingCost | Q1: OrderDate | R1: DeliveryDate | S1: RegionManager | T1: Gross Revenue | U1: Discount AmountA | V1: Net Sales | W1: Delivery Time | X1: Profit | Y1: Is Returned
A2: 44980 | B2: East | C2: Laptop | D2: 14 | E2: 163.6 | F2: Store B | G2: Wholesale | H2: 0 | I2: Eva | J2: 2290.4 | K2: Online | L2: FREESHIP | M2: 0 | N2: REG100000 | O2: Cust 6583 | P2: 43.34 | Q2: 44980 | R2: 44984 | S2: Eric | T2: =D2*E2 -> 2290.4 | U2: =T2*H2 -> 0 | V2: =T2-U2 -> 2290.4 | W2: =R2-Q2 -> 4 | X2: =V2-(E2*D2) -> 0 | Y2: =IF(M2 = "Yes", -V2,0) -> 0
A3: 45645 | B3: South | C3: Phone | D3: 1 | E3: 544.01 | F3: Store A | G3: Retail | H3: 0 | I3: Alice | J3: 544.01 | K3: Gift Card | L3: SAVE10 | M3: 0 | N3: REG100001 | O3: Cust 2144 | P3: 5.3 | Q3: 45645 | R3: 45654 | S3: Sophie | T3: =D3*E3 -> 544.01 | U3: =T3*H3 -> 0 | V3: =T3-U3 -> 544.01 | W3: =R3-Q3 -> 9 | X3: =V3-(E3*D3) -> 0 | Y3: =IF(M3 = "Yes", -V3,0) -> 0
A4: 45056 | B4: North | C4: Desk | D4: 14 | E4: 346.18 | F4: Store B | G4: Wholesale | H4: 0.1 | I4: Alice | J4: 4361.868 | K4: Online | L4: WINTER15 | M4: 0 | N4: REG100002 | O4: Cust 5998 | P4: 20.46 | Q4: 45056 | R4: 45065 | S4: Ryan | T4: =D4*E4 -> 4846.52 | U4: =T4*H4 -> 484.652 | V4: =T4-U4 -> 4361.868 | W4: =R4-Q4 -> 9 | X4: =V4-(E4*D4) -> -484.652 | Y4: =IF(M4 = "Yes", -V4,0) -> 0
A5: 45714 | B5: Central | C5: Chair | D5: 18 | E5: 384.82 | F5: Store A | G5: Wholesale | H5: 0.15 | I5: Frank | J5: 5887.746 | K5: Gift Card | L5: FREESHIP | M5: 0 | N5: REG100003 | O5: Cust 7136 | P5: 27.95 | Q5: 45714 | R5: 45718 | S5: Cameron | T5: =D5*E5 -> 6926.76 | U5: =T5*H5 -> 1039.014 | V5: =T5-U5 -> 5887.746 | W5: =R5-Q5 -> 4 | X5: =V5-(E5*D5) -> -1039.014 | Y5: =IF(M5 = "Yes", -V5,0) -> 0
A6: 45101 | B6: East | C6: Desk | D6: 18 | E6: 237.76 | F6: Store C | G6: Retail | H6: 0 | I6: Carlos | J6: 4279.68 | K6: Online | L6: SAVE10 | M6: 0 | N6: REG100004 | O6: Cust 6506 | P6: 5.73 | Q6: 45101 | R6: 45104 | S6: Eric | T6: =D6*E6 -> 4279.68 | U6: =T6*H6 -> 0 | V6: =T6-U6 -> 4279.68 | W6: =R6-Q6 -> 3 | X6: =V6-(E6*D6) -> 0 | Y6: =IF(M6 = "Yes", -V6,0) -> 0
A7: 45342 | B7: Central | C7: Monitor | D7: 2 | E7: 385.09 | F7: Store D | G7: Wholesale | H7: 0.15 | I7: Diana | J7: 654.653 | K7: Credit Card | M7: 0 | N7: REG100005 | O7: Cust 3909 | P7: 11.92 | Q7: 45342 | R7: 45352 | S7: Cameron | T7: =D7*E7 -> 770.18 | U7: =T7*H7 -> 115.527 | V7: =T7-U7 -> 654.653 | W7: =R7-Q7 -> 10 | X7: =V7-(E7*D7) -> -115.527 | Y7: =IF(M7 = "Yes", -V7,0) -> 0
A8: 44937 | B8: South | C8: Chair | D8: 7 | E8: 17.5 | F8: Store C | G8: Retail | H8: 0.1 | I8: Alice | J8: 110.25 | K8: Debit Card | L8: WINTER15 | M8: 0 | N8: REG100006 | O8: Cust 7887 | P8: 5.02 | Q8: 44937 | R8: 44940 | S8: Sophie | T8: =D8*E8 -> 122.5 | U8: =T8*H8 -> 12.25 | V8: =T8-U8 -> 110.25 | W8: =R8-Q8 -> 3 | X8: =V8-(E8*D8) -> -12.25 | Y8: =IF(M8 = "Yes", -V8,0) -> 0
A9: 44935 | B9: Central | C9: Chair | D9: 3 | E9: 330.22 | F9: Store C | G9: Wholesale | H9: 0.15 | I9: Carlos | J9: 842.061 | K9: Cash | M9: 0 | N9: REG100007 | O9: Cust 5301 | P9: 48.01 | Q9: 44935 | R9: 44937 | S9: Cameron | T9: =D9*E9 -> 990.66 | U9: =T9*H9 -> 148.599 | V9: =T9-U9 -> 842.061 | W9: =R9-Q9 -> 2 | X9: =V9-(E9*D9) -> -148.599 | Y9: =IF(M9 = "Yes", -V9,0) -> 0
A10: 45581 | B10: South | C10: Chair | D10: 3 | E10: 432.04 | F10: Store D | G10: Wholesale | H10: 0.05 | I10: Bob | J10: 1231.314 | K10: Debit Card | L10: FREESHIP | M10: 1 | N10: REG100008 | O10: Cust 2284 | P10: 42.11 | Q10: 45581 | R10: 45583 | S10: Sophie | T10: =D10*E10 -> 1296.12 | U10: =T10*H10 -> 64.806 | V10: =T10-U10 -> 1231.314 | W10: =R10-Q10 -> 2 | X10: =V10-(E10*D10) -> -64.806 | Y10: =IF(M10 = "Yes", -V10,0) -> 0
A11: 45721 | B11: West | C11: Desk | D11: 5 | E11: 323.28 | F11: Store D | G11: Retail | H11: 0.1 | I11: Frank | J11: 1454.76 | K11: Gift Card | L11: SAVE10 | M11: 0 | N11: REG100009 | O11: Cust 3732 | P11: 41.1 | Q11: 45721 | R11: 45729 | S11: Wendy | T11: =D11*E11 -> 1616.4 | U11: =T11*H11 -> 161.64 | V11: =T11-U11 -> 1454.76 | W11: =R11-Q11 -> 8 | X11: =V11-(E11*D11) -> -161.64 | Y11: =IF(M11 = "Yes", -V11,0) -> 0
A12: 45392 | B12: North | C12: Desk | D12: 15 | E12: 523.29 | F12: Store B | G12: Wholesale | H12: 0.15 | I12: Eva | J12: 6671.9475 | K12: Debit Card | M12: 0 | N12: REG100010 | O12: Cust 1462 | P12: 12.14 | Q12: 45392 | R12: 45399 | S12: Ryan | T12: =D12*E12 -> 7849.35 | U12: =T12*H12 -> 1177.4025 | V12: =T12-U12 -> 6671.9475 | W12: =R12-Q12 -> 7 | X12: =V12-(E12*D12) -> -1177.4025 | Y12: =IF(M12 = "Yes", -V12,0) -> 0
A13: 45485 | B13: East | C13: Phone | D13: 19 | E13: 207.35 | F13: Store D | G13: Retail | H13: 0.1 | I13: Eva | J13: 3545.685 | K13: Gift Card | M13: 1 | N13: REG100011 | O13: Cust 4330 | P13: 44.89 | Q13: 45485 | R13: 45491 | S13: Eric | T13: =D13*E13 -> 3939.65 | U13: =T13*H13 -> 393.965 | V13: =T13-U13 -> 3545.685 | W13: =R13-Q13 -> 6 | X13: =V13-(E13*D13) -> -393.965 | Y13: =IF(M13 = "Yes", -V13,0) -> 0
A14: 45128 | B14: Central | C14: Phone | D14: 1 | E14: 120.53 | F14: Store B | G14: Retail | H14: 0.05 | I14: Diana | J14: 114.5035 | K14: Cash | L14: WINTER15 | M14: 0 | N14: REG100012 | O14: Cust 2372 | P14: 20.35 | Q14: 45128 | R14: 45138 | S14: Cameron | T14: =D14*E14 -> 120.53 | U14: =T14*H14 -> 6.0265 | V14: =T14-U14 -> 114.5035 | W14: =R14-Q14 -> 10 | X14: =V14-(E14*D14) -> -6.0265 | Y14: =IF(M14 = "Yes", -V14,0) -> 0
A15: 45675 | B15: West | C15: Tablet | D15: 1 | E15: 157.83 | F15: Store A | G15: Wholesale | H15: 0.15 | I15: Carlos | J15: 134.1555 | K15: Debit Card | M15: 0 | N15: REG100013 | O15: Cust 4672 | P15: 42.82 | Q15: 45675 | R15: 45679 | S15: Wendy | T15: =D15*E15 -> 157.83 | U15: =T15*H15 -> 23.6745 | V15: =T15-U15 -> 134.1555 | W15: =R15-Q15 -> 4 | X15: =V15-(E15*D15) -> -23.6745 | Y15: =IF(M15 = "Yes", -V15,0) -> 0
A16: 45634 | B16: North | C16: Desk | D16: 15 | E16: 220.3 | F16: Store B | G16: Retail | H16: 0.15 | I16: Diana | J16: 2808.825 | K16: Debit Card | M16: 0 | N16: REG100014 | O16: Cust 4548 | P16: 39.66 | Q16: 45634 | R16: 45641 | S16: Ryan | T16: =D16*E16 -> 3304.5 | U16: =T16*H16 -> 495.675 | V16: =T16-U16 -> 2808.825 | W16: =R16-Q16 -> 7 | X16: =V16-(E16*D16) -> -495.675 | Y16: =IF(M16 = "Yes", -V16,0) -> 0
A17: 45788 | B17: West | C17: Chair | D17: 17 | E17: 162.96 | F17: Store A | G17: Wholesale | H17: 0.05 | I17: Eva | J17: 2631.804 | K17: Gift Card | L17: FREESHIP | M17: 0 | N17: REG100015 | O17: Cust 7037 | P17: 8.11 | Q17: 45788 | R17: 45794 | S17: Wendy | T17: =D17*E17 -> 2770.32 | U17: =T17*H17 -> 138.516 | V17: =T17-U17 -> 2631.804 | W17: =R17-Q17 -> 6 | X17: =V17-(E17*D17) -> -138.516 | Y17: =IF(M17 = "Yes", -V17,0) -> 0
A18: 44983 | B18: West | C18: Laptop | D18: 19 | E18: 236.11 | F18: Store D | G18: Wholesale | H18: 0 | I18: Bob | J18: 4486.09 | K18: Online | L18: WINTER15 | M18: 0 | N18: REG100016 | O18: Cust 4975 | P18: 34.11 | Q18: 44983 | R18: 44989 | S18: Wendy | T18: =D18*E18 -> 4486.09 | U18: =T18*H18 -> 0 | V18: =T18-U18 -> 4486.09 | W18: =R18-Q18 -> 6 | X18: =V18-(E18*D18) -> 0 | Y18: =IF(M18 = "Yes", -V18,0) -> 0
A19: 45440 | B19: Central | C19: Desk | D19: 11 | E19: 573.14 | F19: Store D | G19: Retail | H19: 0.05 | I19: Diana | J19: 5989.313 | K19: Cash | L19: SAVE10 | M19: 0 | N19: REG100017 | O19: Cust 8014 | P19: 34.71 | Q19: 45440 | R19: 45444 | S19: Cameron | T19: =D19*E19 -> 6304.54 | U19: =T19*H19 -> 315.227 | V19: =T19-U19 -> 5989.313 | W19: =R19-Q19 -> 4 | X19: =V19-(E19*D19) -> -315.227 | Y19: =IF(M19 = "Yes", -V19,0) -> 0
A20: 45260 | B20: East | C20: Phone | D20: 20 | E20: 519.04 | F20: Store B | G20: Retail | H20: 0.15 | I20: Carlos | J20: 8823.68 | K20: Gift Card | L20: FREESHIP | M20: 0 | N20: REG100018 | O20: Cust 1228 | P20: 19.43 | Q20: 45260 | R20: 45268 | S20: Eric | T20: =D20*E20 -> 10380.8 | U20: =T20*H20 -> 1557.12 | V20: =T20-U20 -> 8823.68 | W20: =R20-Q20 -> 8 | X20: =V20-(E20*D20) -> -1557.12 | Y20: =IF(M20 = "Yes", -V20,0) -> 0
A21: 45099 | B21: West | C21: Desk | D21: 14 | E21: 30.83 | F21: Store B | G21: Retail | H21: 0 | I21: Carlos | J21: 431.62 | K21: Online | L21: WINTER15 | M21: 1 | N21: REG100019 | O21: Cust 4247 | P21: 7.1 | Q21: 45099 | R21: 45109 | S21: Wendy | T21: =D21*E21 -> 431.62 | U21: =T21*H21 -> 0 | V21: =T21-U21 -> 431.62 | W21: =R21-Q21 -> 10 | X21: =V21-(E21*D21) -> 0 | Y21: =IF(M21 = "Yes", -V21,0) -> 0
A22: 45813 | B22: West | C22: Phone | D22: 10 | E22: 319.05 | F22: Store D | G22: Wholesale | H22: 0 | I22: Diana | J22: 3190.5 | K22: Online | M22: 0 | N22: REG100020 | O22: Cust 4199 | P22: 28.43 | Q22: 45813 | R22: 45816 | S22: Wendy | T22: =D22*E22 -> 3190.5 | U22: =T22*H22 -> 0 | V22: =T22-U22 -> 3190.5 | W22: =R22-Q22 -> 3 | X22: =V22-(E22*D22) -> 0 | Y22: =IF(M22 = "Yes", -V22,0) -> 0
A23: 44988 | B23: Central | C23: Chair | D23: 14 | E23: 312.79 | F23: Store A | G23: Retail | H23: 0.05 | I23: Bob | J23: 4160.107 | K23: Online | M23: 1 | N23: REG100021 | O23: Cust 4186 | P23: 46.83 | Q23: 44988 | R23: 44993 | S23: Cameron | T23: =D23*E23 -> 4379.06 | U23: =T23*H23 -> 218.953 | V23: =T23-U23 -> 4160.107 | W23: =R23-Q23 -> 5 | X23: =V23-(E23*D23) -> -218.953 | Y23: =IF(M23 = "Yes", -V23,0) -> 0
A24: 45340 | B24: North | C24: Laptop | D24: 14 | E24: 395.45 | F24: Store C | G24: Retail | H24: 0 | I24: Carlos | J24: 5536.3 | K24: Cash | L24: FREESHIP | M24: 1 | N24: REG100022 | O24: Cust 8137 | P24: 36.45 | Q24: 45340 | R24: 45344 | S24: Ryan | T24: =D24*E24 -> 5536.3 | U24: =T24*H24 -> 0 | V24: =T24-U24 -> 5536.3 | W24: =R24-Q24 -> 4 | X24: =V24-(E24*D24) -> 0 | Y24: =IF(M24 = "Yes", -V24,0) -> 0
A25: 45144 | B25: Central | C25: Laptop | D25: 12 | E25: 472.72 | F25: Store D | G25: Retail | H25: 0.15 | I25: Diana | J25: 4821.744 | K25: Credit Card | M25: 0 | N25: REG100023 | O25: Cust 4638 | P25: 27.97 | Q25: 45144 | R25: 45152 | S25: Cameron | T25: =D25*E25 -> 5672.64 | U25: =T25*H25 -> 850.896 | V25: =T25-U25 -> 4821.744 | W25: =R25-Q25 -> 8 | X25: =V25-(E25*D25) -> -850.896 | Y25: =IF(M25 = "Yes", -V25,0) -> 0
A26: 45435 | B26: North | C26: Desk | D26: 5 | E26: 288.01 | F26: Store A | G26: Wholesale | H26: 0 | I26: Eva | J26: 1440.05 | K26: Credit Card | L26: FREESHIP | M26: 0 | N26: REG100024 | O26: Cust 8538 | P26: 46.69 | Q26: 45435 | R26: 45442 | S26: Ryan | T26: =D26*E26 -> 1440.05 | U26: =T26*H26 -> 0 | V26: =T26-U26 -> 1440.05 | W26: =R26-Q26 -> 7 | X26: =V26-(E26*D26) -> 0 | Y26: =IF(M26 = "Yes", -V26,0) -> 0
A27: 45222 | B27: East | C27: Phone | D27: 13 | E27: 562.29 | F27: Store D | G27: Retail | H27: 0 | I27: Diana | J27: 7309.77 | K27: Gift Card | L27: SAVE10 | M27: 0 | N27: REG100025 | O27: Cust 6322 | P27: 38.13 | Q27: 45222 | R27: 45227 | S27: Eric | T27: =D27*E27 -> 7309.77 | U27: =T27*H27 -> 0 | V27: =T27-U27 -> 7309.77 | W27: =R27-Q27 -> 5 | X27: =V27-(E27*D27) -> 0 | Y27: =IF(M27 = "Yes", -V27,0) -> 0
A28: 45824 | B28: West | C28: Phone | D28: 1 | E28: 101.73 | F28: Store D | G28: Retail | H28: 0 | I28: Frank | J28: 101.73 | K28: Debit Card | L28: WINTER15 | M28: 0 | N28: REG100026 | O28: Cust 2609 | P28: 11.59 | Q28: 45824 | R28: 45833 | S28: Wendy | T28: =D28*E28 -> 101.73 | U28: =T28*H28 -> 0 | V28: =T28-U28 -> 101.73 | W28: =R28-Q28 -> 9 | X28: =V28-(E28*D28) -> 0 | Y28: =IF(M28 = "Yes", -V28,0) -> 0
A29: 44988 | B29: North | C29: Phone | D29: 4 | E29: 279.49 | F29: Store B | G29: Retail | H29: 0 | I29: Diana | J29: 1117.96 | K29: Credit Card | L29: FREESHIP | M29: 0 | N29: REG100027 | O29: Cust 6880 | P29: 24.78 | Q29: 44988 | R29: 44993 | S29: Ryan | T29: =D29*E29 -> 1117.96 | U29: =T29*H29 -> 0 | V29: =T29-U29 -> 1117.96 | W29: =R29-Q29 -> 5 | X29: =V29-(E29*D29) -> 0 | Y29: =IF(M29 = "Yes", -V29,0) -> 0
A30: 45614 | B30: South | C30: Laptop | D30: 1 | E30: 178.55 | F30: Store A | G30: Retail | H30: 0.15 | I30: Carlos | J30: 151.7675 | K30: Debit Card | L30: SAVE10 | M30: 1 | N30: REG100028 | O30: Cust 1997 | P30: 7.61 | Q30: 45614 | R30: 45617 | S30: Sophie | T30: =D30*E30 -> 178.55 | U30: =T30*H30 -> 26.7825 | V30: =T30-U30 -> 151.7675 | W30: =R30-Q30 -> 3 | X30: =V30-(E30*D30) -> -26.7825 | Y30: =IF(M30 = "Yes", -V30,0) -> 0
A31: 45055 | B31: Central | C31: Tablet | D31: 1 | E31: 472.07 | F31: Store A | G31: Wholesale | H31: 0.1 | I31: Carlos | J31: 424.863 | K31: Online | L31: FREESHIP | M31: 0 | N31: REG100029 | O31: Cust 7072 | P31: 33.17 | Q31: 45055 | R31: 45063 | S31: Cameron | T31: =D31*E31 -> 472.07 | U31: =T31*H31 -> 47.207 | V31: =T31-U31 -> 424.863 | W31: =R31-Q31 -> 8 | X31: =V31-(E31*D31) -> -47.207 | Y31: =IF(M31 = "Yes", -V31,0) -> 0
A32: 45633 | B32: North | C32: Tablet | D32: 12 | E32: 306.29 | F32: Store D | G32: Retail | H32: 0 | I32: Frank | J32: 3675.48 | K32: Debit Card | L32: SAVE10 | M32: 0 | N32: REG100030 | O32: Cust 7201 | P32: 37.38 | Q32: 45633 | R32: 45640 | S32: Ryan | T32: =D32*E32 -> 3675.48 | U32: =T32*H32 -> 0 | V32: =T32-U32 -> 3675.48 | W32: =R32-Q32 -> 7 | X32: =V32-(E32*D32) -> 0 | Y32: =IF(M32 = "Yes", -V32,0) -> 0
A33: 45335 | B33: North | C33: Phone | D33: 7 | E33: 434.77 | F33: Store C | G33: Retail | H33: 0.15 | I33: Frank | J33: 2586.8815 | K33: Online | L33: SAVE10 | M33: 0 | N33: REG100031 | O33: Cust 9923 | P33: 12.35 | Q33: 45335 | R33: 45337 | S33: Ryan | T33: =D33*E33 -> 3043.39 | U33: =T33*H33 -> 456.5085 | V33: =T33-U33 -> 2586.8815 | W33: =R33-Q33 -> 2 | X33: =V33-(E33*D33) -> -456.5085 | Y33: =IF(M33 = "Yes", -V33,0) -> 0
A34: 45725 | B34: South | C34: Desk | D34: 6 | E34: 64.98 | F34: Store C | G34: Retail | H34: 0 | I34: Carlos | J34: 389.88 | K34: Debit Card | L34: WINTER15 | M34: 0 | N34: REG100032 | O34: Cust 2205 | P34: 21.25 | Q34: 45725 | R34: 45731 | S34: Sophie | T34: =D34*E34 -> 389.88 | U34: =T34*H34 -> 0 | V34: =T34-U34 -> 389.88 | W34: =R34-Q34 -> 6 | X34: =V34-(E34*D34) -> 0 | Y34: =IF(M34 = "Yes", -V34,0) -> 0
A35: 45021 | B35: Central | C35: Desk | D35: 17 | E35: 476.49 | F35: Store D | G35: Retail | H35: 0 | I35: Alice | J35: 8100.33 | K35: Gift Card | M35: 0 | N35: REG100033 | O35: Cust 6403 | P35: 17.91 | Q35: 45021 | R35: 45027 | S35: Cameron | T35: =D35*E35 -> 8100.33 | U35: =T35*H35 -> 0 | V35: =T35-U35 -> 8100.33 | W35: =R35-Q35 -> 6 | X35: =V35-(E35*D35) -> 0 | Y35: =IF(M35 = "Yes", -V35,0) -> 0
A36: 45785 | B36: North | C36: Monitor | D36: 4 | E36: 559.72 | F36: Store D | G36: Retail | H36: 0.15 | I36: Diana | J36: 1903.048 | K36: Online | L36: SAVE10 | M36: 0 | N36: REG100034 | O36: Cust 3953 | P36: 41.91 | Q36: 45785 | R36: 45789 | S36: Ryan | T36: =D36*E36 -> 2238.88 | U36: =T36*H36 -> 335.832 | V36: =T36-U36 -> 1903.048 | W36: =R36-Q36 -> 4 | X36: =V36-(E36*D36) -> -335.832 | Y36: =IF(M36 = "Yes", -V36,0) -> 0
A37: 45172 | B37: North | C37: Tablet | D37: 14 | E37: 82.14 | F37: Store C | G37: Retail | H37: 0 | I37: Alice | J37: 1149.96 | K37: Credit Card | M37: 0 | N37: REG100035 | O37: Cust 7902 | P37: 12.57 | Q37: 45172 | R37: 45180 | S37: Ryan | T37: =D37*E37 -> 1149.96 | U37: =T37*H37 -> 0 | V37: =T37-U37 -> 1149.96 | W37: =R37-Q37 -> 8 | X37: =V37-(E37*D37) -> 0 | Y37: =IF(M37 = "Yes", -V37,0) -> 0
A38: 45737 | B38: Central | C38: Chair | D38: 9 | E38: 343.21 | F38: Store A | G38: Retail | H38: 0.05 | I38: Carlos | J38: 2934.4455 | K38: Debit Card | L38: FREESHIP | M38: 0 | N38: REG100036 | O38: Cust 9968 | P38: 40.29 | Q38: 45737 | R38: 45744 | S38: Cameron | T38: =D38*E38 -> 3088.89 | U38: =T38*H38 -> 154.4445 | V38: =T38-U38 -> 2934.4455 | W38: =R38-Q38 -> 7 | X38: =V38-(E38*D38) -> -154.4445 | Y38: =IF(M38 = "Yes", -V38,0) -> 0
A39: 45828 | B39: South | C39: Chair | D39: 7 | E39: 301.01 | F39: Store B | G39: Retail | H39: 0.15 | I39: Diana | J39: 1791.0095 | K39: Cash | L39: SAVE10 | M39: 1 | N39: REG100037 | O39: Cust 3787 | P39: 34.97 | Q39: 45828 | R39: 45838 | S39: Sophie | T39: =D39*E39 -> 2107.07 | U39: =T39*H39 -> 316.0605 | V39: =T39-U39 -> 1791.0095 | W39: =R39-Q39 -> 10 | X39: =V39-(E39*D39) -> -316.0605 | Y39: =IF(M39 = "Yes", -V39,0) -> 0
A40: 45337 | B40: Central | C40: Printer | D40: 14 | E40: 428.13 | F40: Store C | G40: Retail | H40: 0.1 | I40: Bob | J40: 5394.438 | K40: Cash | M40: 1 | N40: REG100038 | O40: Cust 2469 | P40: 24.77 | Q40: 45337 | R40: 45347 | S40: Cameron | T40: =D40*E40 -> 5993.82 | U40: =T40*H40 -> 599.382 | V40: =T40-U40 -> 5394.438 | W40: =R40-Q40 -> 10 | X40: =V40-(E40*D40) -> -599.382 | Y40: =IF(M40 = "Yes", -V40,0) -> 0
A41: 45086 | B41: Central | C41: Laptop | D41: 2 | E41: 503.28 | F41: Store D | G41: Retail | H41: 0.15 | I41: Alice | J41: 855.576 | K41: Gift Card | M41: 0 | N41: REG100039 | O41: Cust 6468 | P41: 34.79 | Q41: 45086 | R41: 45094 | S41: Cameron | T41: =D41*E41 -> 1006.56 | U41: =T41*H41 -> 150.984 | V41: =T41-U41 -> 855.576 | W41: =R41-Q41 -> 8 | X41: =V41-(E41*D41) -> -150.984 | Y41: =IF(M41 = "Yes", -V41,0) -> 0
A42: 45148 | B42: South | C42: Printer | D42: 5 | E42: 470.32 | F42: Store A | G42: Retail | H42: 0.1 | I42: Eva | J42: 2116.44 | K42: Debit Card | L42: SAVE10 | M42: 0 | N42: REG100040 | O42: Cust 5312 | P42: 17.77 | Q42: 45148 | R42: 45152 | S42: Sophie | T42: =D42*E42 -> 2351.6 | U42: =T42*H42 -> 235.16 | V42: =T42-U42 -> 2116.44 | W42: =R42-Q42 -> 4 | X42: =V42-(E42*D42) -> -235.16 | Y42: =IF(M42 = "Yes", -V42,0) -> 0
A43: 45459 | B43: Central | C43: Printer | D43: 20 | E43: 65.17 | F43: Store C | G43: Wholesale | H43: 0.05 | I43: Eva | J43: 1238.23 | K43: Gift Card | L43: FREESHIP | M43: 0 | N43: REG100041 | O43: Cust 1482 | P43: 21.72 | Q43: 45459 | R43: 45468 | S43: Cameron | T43: =D43*E43 -> 1303.4 | U43: =T43*H43 -> 65.17 | V43: =T43-U43 -> 1238.23 | W43: =R43-Q43 -> 9 | X43: =V43-(E43*D43) -> -65.17 | Y43: =IF(M43 = "Yes", -V43,0) -> 0
A44: 45130 | B44: South | C44: Laptop | D44: 12 | E44: 36.17 | F44: Store A | G44: Retail | H44: 0 | I44: Eva | J44: 434.04 | K44: Online | L44: WINTER15 | M44: 0 | N44: REG100042 | O44: Cust 7903 | P44: 34.85 | Q44: 45130 | R44: 45133 | S44: Sophie | T44: =D44*E44 -> 434.04 | U44: =T44*H44 -> 0 | V44: =T44-U44 -> 434.04 | W44: =R44-Q44 -> 3 | X44: =V44-(E44*D44) -> 0 | Y44: =IF(M44 = "Yes", -V44,0) -> 0
A45: 45066 | B45: Central | C45: Printer | D45: 4 | E45: 459.31 | F45: Store D | G45: Wholesale | H45: 0.15 | I45: Carlos | J45: 1561.654 | K45: Gift Card | L45: WINTER15 | M45: 1 | N45: REG100043 | O45: Cust 9605 | P45: 27.39 | Q45: 45066 | R45: 45073 | S45: Cameron | T45: =D45*E45 -> 1837.24 | U45: =T45*H45 -> 275.586 | V45: =T45-U45 -> 1561.654 | W45: =R45-Q45 -> 7 | X45: =V45-(E45*D45) -> -275.586 | Y45: =IF(M45 = "Yes", -V45,0) -> 0
A46: 45107 | B46: South | C46: Laptop | D46: 2 | E46: 416.06 | F46: Store D | G46: Retail | H46: 0.05 | I46: Eva | J46: 790.514 | K46: Debit Card | L46: SAVE10 | M46: 0 | N46: REG100044 | O46: Cust 3298 | P46: 11.62 | Q46: 45107 | R46: 45111 | S46: Sophie | T46: =D46*E46 -> 832.12 | U46: =T46*H46 -> 41.606 | V46: =T46-U46 -> 790.514 | W46: =R46-Q46 -> 4 | X46: =V46-(E46*D46) -> -41.606 | Y46: =IF(M46 = "Yes", -V46,0) -> 0
A47: 45447 | B47: South | C47: Tablet | D47: 16 | E47: 302.58 | F47: Store D | G47: Retail | H47: 0 | I47: Alice | J47: 4841.28 | K47: Online | L47: WINTER15 | M47: 1 | N47: REG100045 | O47: Cust 5533 | P47: 20.76 | Q47: 45447 | R47: 45457 | S47: Sophie | T47: =D47*E47 -> 4841.28 | U47: =T47*H47 -> 0 | V47: =T47-U47 -> 4841.28 | W47: =R47-Q47 -> 10 | X47: =V47-(E47*D47) -> 0 | Y47: =IF(M47 = "Yes", -V47,0) -> 0
A48: 45691 | B48: West | C48: Chair | D48: 11 | E48: 33.13 | F48: Store A | G48: Retail | H48: 0.15 | I48: Frank | J48: 309.7655 | K48: Online | L48: FREESHIP | M48: 0 | N48: REG100046 | O48: Cust 6362 | P48: 24.95 | Q48: 45691 | R48: 45693 | S48: Wendy | T48: =D48*E48 -> 364.43 | U48: =T48*H48 -> 54.6645 | V48: =T48-U48 -> 309.7655 | W48: =R48-Q48 -> 2 | X48: =V48-(E48*D48) -> -54.6645 | Y48: =IF(M48 = "Yes", -V48,0) -> 0
A49: 45300 | B49: East | C49: Tablet | D49: 8 | E49: 582.52 | F49: Store D | G49: Retail | H49: 0.15 | I49: Frank | J49: 3961.136 | K49: Gift Card | L49: WINTER15 | M49: 0 | N49: REG100047 | O49: Cust 4826 | P49: 6.47 | Q49: 45300 | R49: 45304 | S49: Eric | T49: =D49*E49 -> 4660.16 | U49: =T49*H49 -> 699.024 | V49: =T49-U49 -> 3961.136 | W49: =R49-Q49 -> 4 | X49: =V49-(E49*D49) -> -699.024 | Y49: =IF(M49 = "Yes", -V49,0) -> 0
A50: 45365 | B50: North | C50: Desk | D50: 5 | E50: 165.15 | F50: Store A | G50: Retail | H50: 0.1 | I50: Eva | J50: 743.175 | K50: Gift Card | M50: 0 | N50: REG100048 | O50: Cust 2171 | P50: 20.57 | Q50: 45365 | R50: 45367 | S50: Ryan | T50: =D50*E50 -> 825.75 | U50: =T50*H50 -> 82.575 | V50: =T50-U50 -> 743.175 | W50: =R50-Q50 -> 2 | X50: =V50-(E50*D50) -> -82.575 | Y50: =IF(M50 = "Yes", -V50,0) -> 0
A51: 45541 | B51: West | C51: Monitor | D51: 14 | E51: 242.82 | F51: Store D | G51: Wholesale | H51: 0.15 | I51: Alice | J51: 2889.558 | K51: Cash | L51: WINTER15 | M51: 1 | N51: REG100049 | O51: Cust 4005 | P51: 20.71 | Q51: 45541 | R51: 45548 | S51: Wendy | T51: =D51*E51 -> 3399.48 | U51: =T51*H51 -> 509.922 | V51: =T51-U51 -> 2889.558 | W51: =R51-Q51 -> 7 | X51: =V51-(E51*D51) -> -509.922 | Y51: =IF(M51 = "Yes", -V51,0) -> 0
A52: 45002 | B52: East | C52: Monitor | D52: 13 | E52: 65.99 | F52: Store A | G52: Wholesale | H52: 0.1 | I52: Frank | J52: 772.083 | K52: Cash | L52: WINTER15 | M52: 0 | N52: REG100050 | O52: Cust 7032 | P52: 12.87 | Q52: 45002 | R52: 45005 | S52: Eric | T52: =D52*E52 -> 857.87 | U52: =T52*H52 -> 85.787 | V52: =T52-U52 -> 772.083 | W52: =R52-Q52 -> 3 | X52: =V52-(E52*D52) -> -85.787 | Y52: =IF(M52 = "Yes", -V52,0) -> 0
A53: 45674 | B53: West | C53: Chair | D53: 2 | E53: 251.69 | F53: Store C | G53: Wholesale | H53: 0 | I53: Alice | J53: 503.38 | K53: Debit Card | L53: FREESHIP | M53: 0 | N53: REG100051 | O53: Cust 7167 | P53: 42.49 | Q53: 45674 | R53: 45681 | S53: Wendy | T53: =D53*E53 -> 503.38 | U53: =T53*H53 -> 0 | V53: =T53-U53 -> 503.38 | W53: =R53-Q53 -> 7 | X53: =V53-(E53*D53) -> 0 | Y53: =IF(M53 = "Yes", -V53,0) -> 0
A54: 45547 | B54: South | C54: Laptop | D54: 1 | E54: 269.41 | F54: Store B | G54: Wholesale | H54: 0.1 | I54: Eva | J54: 242.469 | K54: Cash | L54: WINTER15 | M54: 1 | N54: REG100052 | O54: Cust 5702 | P54: 19.22 | Q54: 45547 | R54: 45553 | S54: Sophie | T54: =D54*E54 -> 269.41 | U54: =T54*H54 -> 26.941 | V54: =T54-U54 -> 242.469 | W54: =R54-Q54 -> 6 | X54: =V54-(E54*D54) -> -26.941 | Y54: =IF(M54 = "Yes", -V54,0) -> 0
A55: 45296 | B55: South | C55: Monitor | D55: 2 | E55: 371.3 | F55: Store B | G55: Wholesale | H55: 0.05 | I55: Bob | J55: 705.47 | K55: Credit Card | L55: SAVE10 | M55: 0 | N55: REG100053 | O55: Cust 4944 | P55: 36.51 | Q55: 45296 | R55: 45306 | S55: Sophie | T55: =D55*E55 -> 742.6 | U55: =T55*H55 -> 37.13 | V55: =T55-U55 -> 705.47 | W55: =R55-Q55 -> 10 | X55: =V55-(E55*D55) -> -37.13 | Y55: =IF(M55 = "Yes", -V55,0) -> 0
A56: 45401 | B56: West | C56: Tablet | D56: 11 | E56: 288.24 | F56: Store A | G56: Wholesale | H56: 0.15 | I56: Diana | J56: 2695.044 | K56: Online | M56: 0 | N56: REG100054 | O56: Cust 8149 | P56: 37.39 | Q56: 45401 | R56: 45407 | S56: Wendy | T56: =D56*E56 -> 3170.64 | U56: =T56*H56 -> 475.596 | V56: =T56-U56 -> 2695.044 | W56: =R56-Q56 -> 6 | X56: =V56-(E56*D56) -> -475.596 | Y56: =IF(M56 = "Yes", -V56,0) -> 0
A57: 45819 | B57: Central | C57: Tablet | D57: 11 | E57: 232.75 | F57: Store D | G57: Wholesale | H57: 0.05 | I57: Eva | J57: 2432.2375 | K57: Credit Card | L57: SAVE10 | M57: 0 | N57: REG100055 | O57: Cust 3638 | P57: 36.33 | Q57: 45819 | R57: 45829 | S57: Cameron | T57: =D57*E57 -> 2560.25 | U57: =T57*H57 -> 128.0125 | V57: =T57-U57 -> 2432.2375 | W57: =R57-Q57 -> 10 | X57: =V57-(E57*D57) -> -128.0125 | Y57: =IF(M57 = "Yes", -V57,0) -> 0
A58: 45722 | B58: East | C58: Phone | D58: 17 | E58: 146.28 | F58: Store B | G58: Retail | H58: 0.15 | I58: Carlos | J58: 2113.746 | K58: Cash | L58: SAVE10 | M58: 0 | N58: REG100056 | O58: Cust 9973 | P58: 7.84 | Q58: 45722 | R58: 45731 | S58: Eric | T58: =D58*E58 -> 2486.76 | U58: =T58*H58 -> 373.014 | V58: =T58-U58 -> 2113.746 | W58: =R58-Q58 -> 9 | X58: =V58-(E58*D58) -> -373.014 | Y58: =IF(M58 = "Yes", -V58,0) -> 0
A59: 45070 | B59: East | C59: Chair | D59: 5 | E59: 100.38 | F59: Store C | G59: Retail | H59: 0.1 | I59: Eva | J59: 451.71 | K59: Gift Card | L59: WINTER15 | M59: 1 | N59: REG100057 | O59: Cust 4214 | P59: 18.35 | Q59: 45070 | R59: 45072 | S59: Eric | T59: =D59*E59 -> 501.9 | U59: =T59*H59 -> 50.19 | V59: =T59-U59 -> 451.71 | W59: =R59-Q59 -> 2 | X59: =V59-(E59*D59) -> -50.19 | Y59: =IF(M59 = "Yes", -V59,0) -> 0
A60: 44953 | B60: South | C60: Phone | D60: 11 | E60: 375.48 | F60: Store B | G60: Retail | H60: 0.05 | I60: Bob | J60: 3923.766 | K60: Debit Card | L60: WINTER15 | M60: 0 | N60: REG100058 | O60: Cust 2647 | P60: 15.95 | Q60: 44953 | R60: 44960 | S60: Sophie | T60: =D60*E60 -> 4130.28 | U60: =T60*H60 -> 206.514 | V60: =T60-U60 -> 3923.766 | W60: =R60-Q60 -> 7 | X60: =V60-(E60*D60) -> -206.514 | Y60: =IF(M60 = "Yes", -V60,0) -> 0
A61: 45372 | B61: South | C61: Laptop | D61: 18 | E61: 316.89 | F61: Store B | G61: Wholesale | H61: 0.05 | I61: Bob | J61: 5418.819 | K61: Cash | L61: FREESHIP | M61: 0 | N61: REG100059 | O61: Cust 3552 | P61: 15.69 | Q61: 45372 | R61: 45378 | S61: Sophie | T61: =D61*E61 -> 5704.02 | U61: =T61*H61 -> 285.201 | V61: =T61-U61 -> 5418.819 | W61: =R61-Q61 -> 6 | X61: =V61-(E61*D61) -> -285.201 | Y61: =IF(M61 = "Yes", -V61,0) -> 0
A62: 45682 | B62: West | C62: Laptop | D62: 20 | E62: 295.06 | F62: Store D | G62: Retail | H62: 0.15 | I62: Frank | J62: 5016.02 | K62: Online | L62: SAVE10 | M62: 1 | N62: REG100060 | O62: Cust 3354 | P62: 13.66 | Q62: 45682 | R62: 45688 | S62: Wendy | T62: =D62*E62 -> 5901.2 | U62: =T62*H62 -> 885.18 | V62: =T62-U62 -> 5016.02 | W62: =R62-Q62 -> 6 | X62: =V62-(E62*D62) -> -885.18 | Y62: =IF(M62 = "Yes", -V62,0) -> 0
A63: 45089 | B63: Central | C63: Phone | D63: 8 | E63: 301.68 | F63: Store D | G63: Retail | H63: 0 | I63: Eva | J63: 2413.44 | K63: Cash | L63: SAVE10 | M63: 0 | N63: REG100061 | O63: Cust 3903 | P63: 36.54 | Q63: 45089 | R63: 45098 | S63: Cameron | T63: =D63*E63 -> 2413.44 | U63: =T63*H63 -> 0 | V63: =T63-U63 -> 2413.44 | W63: =R63-Q63 -> 9 | X63: =V63-(E63*D63) -> 0 | Y63: =IF(M63 = "Yes", -V63,0) -> 0
A64: 45738 | B64: Central | C64: Chair | D64: 3 | E64: 475.39 | F64: Store B | G64: Retail | H64: 0.1 | I64: Alice | J64: 1283.553 | K64: Gift Card | M64: 0 | N64: REG100062 | O64: Cust 5358 | P64: 15.62 | Q64: 45738 | R64: 45742 | S64: Cameron | T64: =D64*E64 -> 1426.17 | U64: =T64*H64 -> 142.617 | V64: =T64-U64 -> 1283.553 | W64: =R64-Q64 -> 4 | X64: =V64-(E64*D64) -> -142.617 | Y64: =IF(M64 = "Yes", -V64,0) -> 0
A65: 45346 | B65: Central | C65: Desk | D65: 16 | E65: 47.25 | F65: Store D | G65: Retail | H65: 0.15 | I65: Bob | J65: 642.6 | K65: Debit Card | L65: FREESHIP | M65: 0 | N65: REG100063 | O65: Cust 8144 | P65: 29.5 | Q65: 45346 | R65: 45349 | S65: Cameron | T65: =D65*E65 -> 756 | U65: =T65*H65 -> 113.4 | V65: =T65-U65 -> 642.6 | W65: =R65-Q65 -> 3 | X65: =V65-(E65*D65) -> -113.4 | Y65: =IF(M65 = "Yes", -V65,0) -> 0
A66: 45269 | B66: South | C66: Chair | D66: 15 | E66: 511.17 | F66: Store B | G66: Wholesale | H66: 0 | I66: Frank | J66: 7667.55 | K66: Online | L66: FREESHIP | M66: 0 | N66: REG100064 | O66: Cust 6747 | P66: 21.77 | Q66: 45269 | R66: 45272 | S66: Sophie | T66: =D66*E66 -> 7667.55 | U66: =T66*H66 -> 0 | V66: =T66-U66 -> 7667.55 | W66: =R66-Q66 -> 3 | X66: =V66-(E66*D66) -> 0 | Y66: =IF(M66 = "Yes", -V66,0) -> 0
A67: 45200 | B67: Central | C67: Monitor | D67: 3 | E67: 66.58 | F67: Store B | G67: Retail | H67: 0.1 | I67: Frank | J67: 179.766 | K67: Debit Card | L67: FREESHIP | M67: 0 | N67: REG100065 | O67: Cust 8330 | P67: 22.43 | Q67: 45200 | R67: 45204 | S67: Cameron | T67: =D67*E67 -> 199.74 | U67: =T67*H67 -> 19.974 | V67: =T67-U67 -> 179.766 | W67: =R67-Q67 -> 4 | X67: =V67-(E67*D67) -> -19.974 | Y67: =IF(M67 = "Yes", -V67,0) -> 0
A68: 45138 | B68: West | C68: Tablet | D68: 5 | E68: 490.52 | F68: Store D | G68: Wholesale | H68: 0.05 | I68: Frank | J68: 2329.97 | K68: Online | M68: 0 | N68: REG100066 | O68: Cust 7186 | P68: 12.24 | Q68: 45138 | R68: 45145 | S68: Wendy | T68: =D68*E68 -> 2452.6 | U68: =T68*H68 -> 122.63 | V68: =T68-U68 -> 2329.97 | W68: =R68-Q68 -> 7 | X68: =V68-(E68*D68) -> -122.63 | Y68: =IF(M68 = "Yes", -V68,0) -> 0
A69: 45650 | B69: South | C69: Chair | D69: 8 | E69: 405.96 | F69: Store A | G69: Wholesale | H69: 0.05 | I69: Carlos | J69: 3085.296 | K69: Credit Card | L69: WINTER15 | M69: 0 | N69: REG100067 | O69: Cust 8287 | P69: 41.27 | Q69: 45650 | R69: 45657 | S69: Sophie | T69: =D69*E69 -> 3247.68 | U69: =T69*H69 -> 162.384 | V69: =T69-U69 -> 3085.296 | W69: =R69-Q69 -> 7 | X69: =V69-(E69*D69) -> -162.384 | Y69: =IF(M69 = "Yes", -V69,0) -> 0
A70: 45611 | B70: North | C70: Phone | D70: 1 | E70: 159.41 | F70: Store B | G70: Retail | H70: 0.1 | I70: Bob | J70: 143.469 | K70: Credit Card | L70: FREESHIP | M70: 0 | N70: REG100068 | O70: Cust 3986 | P70: 35.14 | Q70: 45611 | R70: 45615 | S70: Ryan | T70: =D70*E70 -> 159.41 | U70: =T70*H70 -> 15.941 | V70: =T70-U70 -> 143.469 | W70: =R70-Q70 -> 4 | X70: =V70-(E70*D70) -> -15.941 | Y70: =IF(M70 = "Yes", -V70,0) -> 0
A71: 45729 | B71: West | C71: Monitor | D71: 16 | E71: 38.49 | F71: Store C | G71: Retail | H71: 0.15 | I71: Carlos | J71: 523.464 | K71: Debit Card | L71: SAVE10 | M71: 0 | N71: REG100069 | O71: Cust 3213 | P71: 8.38 | Q71: 45729 | R71: 45738 | S71: Wendy | T71: =D71*E71 -> 615.84 | U71: =T71*H71 -> 92.376 | V71: =T71-U71 -> 523.464 | W71: =R71-Q71 -> 9 | X71: =V71-(E71*D71) -> -92.376 | Y71: =IF(M71 = "Yes", -V71,0) -> 0
A72: 45354 | B72: East | C72: Tablet | D72: 15 | E72: 328.36 | F72: Store D | G72: Retail | H72: 0.15 | I72: Alice | J72: 4186.59 | K72: Gift Card | L72: WINTER15 | M72: 0 | N72: REG100070 | O72: Cust 1907 | P72: 15.76 | Q72: 45354 | R72: 45363 | S72: Eric | T72: =D72*E72 -> 4925.4 | U72: =T72*H72 -> 738.81 | V72: =T72-U72 -> 4186.59 | W72: =R72-Q72 -> 9 | X72: =V72-(E72*D72) -> -738.81 | Y72: =IF(M72 = "Yes", -V72,0) -> 0
A73: 44968 | B73: Central | C73: Tablet | D73: 20 | E73: 548.01 | F73: Store A | G73: Wholesale | H73: 0.1 | I73: Eva | J73: 9864.18 | K73: Credit Card | L73: WINTER15 | M73: 1 | N73: REG100071 | O73: Cust 4639 | P73: 5.89 | Q73: 44968 | R73: 44971 | S73: Cameron | T73: =D73*E73 -> 10960.2 | U73: =T73*H73 -> 1096.02 | V73: =T73-U73 -> 9864.18 | W73: =R73-Q73 -> 3 | X73: =V73-(E73*D73) -> -1096.02 | Y73: =IF(M73 = "Yes", -V73,0) -> 0
A74: 45225 | B74: South | C74: Desk | D74: 13 | E74: 484.45 | F74: Store B | G74: Wholesale | H74: 0.05 | I74: Carlos | J74: 5982.9575 | K74: Gift Card | L74: WINTER15 | M74: 1 | N74: REG100072 | O74: Cust 4153 | P74: 6.57 | Q74: 45225 | R74: 45235 | S74: Sophie | T74: =D74*E74 -> 6297.85 | U74: =T74*H74 -> 314.8925 | V74: =T74-U74 -> 5982.9575 | W74: =R74-Q74 -> 10 | X74: =V74-(E74*D74) -> -314.8925 | Y74: =IF(M74 = "Yes", -V74,0) -> 0
A75: 45220 | B75: South | C75: Monitor | D75: 13 | E75: 195.84 | F75: Store A | G75: Wholesale | H75: 0.05 | I75: Alice | J75: 2418.624 | K75: Credit Card | M75: 0 | N75: REG100073 | O75: Cust 7096 | P75: 33.52 | Q75: 45220 | R75: 45227 | S75: Sophie | T75: =D75*E75 -> 2545.92 | U75: =T75*H75 -> 127.296 | V75: =T75-U75 -> 2418.624 | W75: =R75-Q75 -> 7 | X75: =V75-(E75*D75) -> -127.296 | Y75: =IF(M75 = "Yes", -V75,0) -> 0
A76: 45305 | B76: Central | C76: Tablet | D76: 19 | E76: 29.94 | F76: Store D | G76: Retail | H76: 0.15 | I76: Diana | J76: 483.531 | K76: Debit Card | L76: FREESHIP | M76: 0 | N76: REG100074 | O76: Cust 3806 | P76: 33.59 | Q76: 45305 | R76: 45311 | S76: Cameron | T76: =D76*E76 -> 568.86 | U76: =T76*H76 -> 85.329 | V76: =T76-U76 -> 483.531 | W76: =R76-Q76 -> 6 | X76: =V76-(E76*D76) -> -85.329 | Y76: =IF(M76 = "Yes", -V76,0) -> 0
A77: 45134 | B77: Central | C77: Desk | D77: 10 | E77: 553.91 | F77: Store D | G77: Wholesale | H77: 0.1 | I77: Eva | J77: 4985.19 | K77: Online | M77: 0 | N77: REG100075 | O77: Cust 9345 | P77: 31.3 | Q77: 45134 | R77: 45138 | S77: Cameron | T77: =D77*E77 -> 5539.1 | U77: =T77*H77 -> 553.91 | V77: =T77-U77 -> 4985.19 | W77: =R77-Q77 -> 4 | X77: =V77-(E77*D77) -> -553.91 | Y77: =IF(M77 = "Yes", -V77,0) -> 0
A78: 45588 | B78: South | C78: Phone | D78: 14 | E78: 445.52 | F78: Store B | G78: Retail | H78: 0.1 | I78: Bob | J78: 5613.552 | K78: Online | L78: SAVE10 | M78: 0 | N78: REG100076 | O78: Cust 4456 | P78: 14.41 | Q78: 45588 | R78: 45590 | S78: Sophie | T78: =D78*E78 -> 6237.28 | U78: =T78*H78 -> 623.728 | V78: =T78-U78 -> 5613.552 | W78: =R78-Q78 -> 2 | X78: =V78-(E78*D78) -> -623.728 | Y78: =IF(M78 = "Yes", -V78,0) -> 0
A79: 45195 | B79: South | C79: Chair | D79: 5 | E79: 551.58 | F79: Store B | G79: Retail | H79: 0.15 | I79: Alice | J79: 2344.215 | K79: Online | L79: WINTER15 | M79: 1 | N79: REG100077 | O79: Cust 1089 | P79: 7.87 | Q79: 45195 | R79: 45200 | S79: Sophie | T79: =D79*E79 -> 2757.9 | U79: =T79*H79 -> 413.685 | V79: =T79-U79 -> 2344.215 | W79: =R79-Q79 -> 5 | X79: =V79-(E79*D79) -> -413.685 | Y79: =IF(M79 = "Yes", -V79,0) -> 0
A80: 45276 | B80: East | C80: Phone | D80: 13 | E80: 241.4 | F80: Store D | G80: Retail | H80: 0 | I80: Carlos | J80: 3138.2 | K80: Gift Card | L80: SAVE10 | M80: 0 | N80: REG100078 | O80: Cust 7230 | P80: 49.05 | Q80: 45276 | R80: 45280 | S80: Eric | T80: =D80*E80 -> 3138.2 | U80: =T80*H80 -> 0 | V80: =T80-U80 -> 3138.2 | W80: =R80-Q80 -> 4 | X80: =V80-(E80*D80) -> 0 | Y80: =IF(M80 = "Yes", -V80,0) -> 0
A81: 45293 | B81: Central | C81: Printer | D81: 19 | E81: 351.93 | F81: Store A | G81: Wholesale | H81: 0 | I81: Alice | J81: 6686.67 | K81: Credit Card | M81: 0 | N81: REG100079 | O81: Cust 6597 | P81: 39.98 | Q81: 45293 | R81: 45296 | S81: Cameron | T81: =D81*E81 -> 6686.67 | U81: =T81*H81 -> 0 | V81: =T81-U81 -> 6686.67 | W81: =R81-Q81 -> 3 | X81: =V81-(E81*D81) -> 0 | Y81: =IF(M81 = "Yes", -V81,0) -> 0
A82: 45338 | B82: North | C82: Phone | D82: 4 | E82: 83.75 | F82: Store A | G82: Retail | H82: 0.05 | I82: Alice | J82: 318.25 | K82: Debit Card | L82: SAVE10 | M82: 1 | N82: REG100080 | O82: Cust 4108 | P82: 38.82 | Q82: 45338 | R82: 45347 | S82: Ryan | T82: =D82*E82 -> 335 | U82: =T82*H82 -> 16.75 | V82: =T82-U82 -> 318.25 | W82: =R82-Q82 -> 9 | X82: =V82-(E82*D82) -> -16.75 | Y82: =IF(M82 = "Yes", -V82,0) -> 0
A83: 45415 | B83: East | C83: Monitor | D83: 5 | E83: 416.95 | F83: Store A | G83: Wholesale | H83: 0.15 | I83: Frank | J83: 1772.0375 | K83: Online | M83: 1 | N83: REG100081 | O83: Cust 2883 | P83: 24.03 | Q83: 45415 | R83: 45424 | S83: Eric | T83: =D83*E83 -> 2084.75 | U83: =T83*H83 -> 312.7125 | V83: =T83-U83 -> 1772.0375 | W83: =R83-Q83 -> 9 | X83: =V83-(E83*D83) -> -312.7125 | Y83: =IF(M83 = "Yes", -V83,0) -> 0
A84: 45073 | B84: West | C84: Monitor | D84: 18 | E84: 142.43 | F84: Store C | G84: Retail | H84: 0.05 | I84: Bob | J84: 2435.553 | K84: Credit Card | L84: SAVE10 | M84: 1 | N84: REG100082 | O84: Cust 5018 | P84: 12.38 | Q84: 45073 | R84: 45079 | S84: Wendy | T84: =D84*E84 -> 2563.74 | U84: =T84*H84 -> 128.187 | V84: =T84-U84 -> 2435.553 | W84: =R84-Q84 -> 6 | X84: =V84-(E84*D84) -> -128.187 | Y84: =IF(M84 = "Yes", -V84,0) -> 0
A85: 44931 | B85: East | C85: Desk | D85: 12 | E85: 582.52 | F85: Store A | G85: Wholesale | H85: 0 | I85: Bob | J85: 6990.24 | K85: Credit Card | L85: FREESHIP | M85: 0 | N85: REG100083 | O85: Cust 1231 | P85: 41.16 | Q85: 44931 | R85: 44937 | S85: Eric | T85: =D85*E85 -> 6990.24 | U85: =T85*H85 -> 0 | V85: =T85-U85 -> 6990.24 | W85: =R85-Q85 -> 6 | X85: =V85-(E85*D85) -> 0 | Y85: =IF(M85 = "Yes", -V85,0) -> 0
A86: 45798 | B86: East | C86: Chair | D86: 20 | E86: 129.56 | F86: Store A | G86: Retail | H86: 0.15 | I86: Diana | J86: 2202.52 | K86: Online | L86: WINTER15 | M86: 0 | N86: REG100084 | O86: Cust 2209 | P86: 40.21 | Q86: 45798 | R86: 45800 | S86: Eric | T86: =D86*E86 -> 2591.2 | U86: =T86*H86 -> 388.68 | V86: =T86-U86 -> 2202.52 | W86: =R86-Q86 -> 2 | X86: =V86-(E86*D86) -> -388.68 | Y86: =IF(M86 = "Yes", -V86,0) -> 0
A87: 45128 | B87: Central | C87: Tablet | D87: 17 | E87: 431.82 | F87: Store B | G87: Retail | H87: 0 | I87: Eva | J87: 7340.94 | K87: Gift Card | L87: FREESHIP | M87: 1 | N87: REG100085 | O87: Cust 6684 | P87: 37.75 | Q87: 45128 | R87: 45132 | S87: Cameron | T87: =D87*E87 -> 7340.94 | U87: =T87*H87 -> 0 | V87: =T87-U87 -> 7340.94 | W87: =R87-Q87 -> 4 | X87: =V87-(E87*D87) -> 0 | Y87: =IF(M87 = "Yes", -V87,0) -> 0
A88: 45802 | B88: East | C88: Laptop | D88: 15 | E88: 15.85 | F88: Store C | G88: Retail | H88: 0 | I88: Bob | J88: 237.75 | K88: Debit Card | L88: WINTER15 | M88: 0 | N88: REG100086 | O88: Cust 5289 | P88: 23.49 | Q88: 45802 | R88: 45811 | S88: Eric | T88: =D88*E88 -> 237.75 | U88: =T88*H88 -> 0 | V88: =T88-U88 -> 237.75 | W88: =R88-Q88 -> 9 | X88: =V88-(E88*D88) -> 0 | Y88: =IF(M88 = "Yes", -V88,0) -> 0
A89: 45612 | B89: South | C89: Tablet | D89: 20 | E89: 548.34 | F89: Store B | G89: Retail | H89: 0.1 | I89: Bob | J89: 9870.12 | K89: Gift Card | L89: WINTER15 | M89: 0 | N89: REG100087 | O89: Cust 9159 | P89: 33.47 | Q89: 45612 | R89: 45618 | S89: Sophie | T89: =D89*E89 -> 10966.8 | U89: =T89*H89 -> 1096.68 | V89: =T89-U89 -> 9870.12 | W89: =R89-Q89 -> 6 | X89: =V89-(E89*D89) -> -1096.68 | Y89: =IF(M89 = "Yes", -V89,0) -> 0
A90: 45249 | B90: North | C90: Laptop | D90: 16 | E90: 525.83 | F90: Store C | G90: Wholesale | H90: 0.05 | I90: Frank | J90: 7992.616 | K90: Online | M90: 0 | N90: REG100088 | O90: Cust 4844 | P90: 36.47 | Q90: 45249 | R90: 45255 | S90: Ryan | T90: =D90*E90 -> 8413.28 | U90: =T90*H90 -> 420.664 | V90: =T90-U90 -> 7992.616 | W90: =R90-Q90 -> 6 | X90: =V90-(E90*D90) -> -420.664 | Y90: =IF(M90 = "Yes", -V90,0) -> 0
A91: 45669 | B91: Central | C91: Laptop | D91: 15 | E91: 411.38 | F91: Store A | G91: Wholesale | H91: 0.05 | I91: Bob | J91: 5862.165 | K91: Online | L91: SAVE10 | M91: 0 | N91: REG100089 | O91: Cust 3273 | P91: 48.51 | Q91: 45669 | R91: 45678 | S91: Cameron | T91: =D91*E91 -> 6170.7 | U91: =T91*H91 -> 308.535 | V91: =T91-U91 -> 5862.165 | W91: =R91-Q91 -> 9 | X91: =V91-(E91*D91) -> -308.535 | Y91: =IF(M91 = "Yes", -V91,0) -> 0
A92: 45014 | B92: North | C92: Monitor | D92: 19 | E92: 559.95 | F92: Store A | G92: Wholesale | H92: 0.1 | I92: Carlos | J92: 9575.145 | K92: Credit Card | L92: WINTER15 | M92: 0 | N92: REG100090 | O92: Cust 8160 | P92: 18.3 | Q92: 45014 | R92: 45019 | S92: Ryan | T92: =D92*E92 -> 10639.05 | U92: =T92*H92 -> 1063.905 | V92: =T92-U92 -> 9575.145 | W92: =R92-Q92 -> 5 | X92: =V92-(E92*D92) -> -1063.905 | Y92: =IF(M92 = "Yes", -V92,0) -> 0
A93: 45717 | B93: North | C93: Desk | D93: 8 | E93: 179.9 | F93: Store C | G93: Retail | H93: 0.05 | I93: Carlos | J93: 1367.24 | K93: Online | L93: SAVE10 | M93: 0 | N93: REG100091 | O93: Cust 4439 | P93: 14.8 | Q93: 45717 | R93: 45721 | S93: Ryan | T93: =D93*E93 -> 1439.2 | U93: =T93*H93 -> 71.96 | V93: =T93-U93 -> 1367.24 | W93: =R93-Q93 -> 4 | X93: =V93-(E93*D93) -> -71.96 | Y93: =IF(M93 = "Yes", -V93,0) -> 0
A94: 45217 | B94: North | C94: Chair | D94: 12 | E94: 494.15 | F94: Store B | G94: Wholesale | H94: 0.15 | I94: Diana | J94: 5040.33 | K94: Online | L94: SAVE10 | M94: 1 | N94: REG100092 | O94: Cust 1127 | P94: 18.05 | Q94: 45217 | R94: 45219 | S94: Ryan | T94: =D94*E94 -> 5929.8 | U94: =T94*H94 -> 889.47 | V94: =T94-U94 -> 5040.33 | W94: =R94-Q94 -> 2 | X94: =V94-(E94*D94) -> -889.47 | Y94: =IF(M94 = "Yes", -V94,0) -> 0
A95: 45760 | B95: East | C95: Desk | D95: 10 | E95: 462.99 | F95: Store C | G95: Wholesale | H95: 0 | I95: Bob | J95: 4629.9 | K95: Credit Card | L95: WINTER15 | M95: 0 | N95: REG100093 | O95: Cust 4696 | P95: 5.01 | Q95: 45760 | R95: 45762 | S95: Eric | T95: =D95*E95 -> 4629.9 | U95: =T95*H95 -> 0 | V95: =T95-U95 -> 4629.9 | W95: =R95-Q95 -> 2 | X95: =V95-(E95*D95) -> 0 | Y95: =IF(M95 = "Yes", -V95,0) -> 0
A96: 45790 | B96: Central | C96: Laptop | D96: 7 | E96: 460.24 | F96: Store A | G96: Retail | H96: 0.05 | I96: Alice | J96: 3060.596 | K96: Cash | L96: SAVE10 | M96: 1 | N96: REG100094 | O96: Cust 3014 | P96: 11.54 | Q96: 45790 | R96: 45800 | S96: Cameron | T96: =D96*E96 -> 3221.68 | U96: =T96*H96 -> 161.084 | V96: =T96-U96 -> 3060.596 | W96: =R96-Q96 -> 10 | X96: =V96-(E96*D96) -> -161.084 | Y96: =IF(M96 = "Yes", -V96,0) -> 0
A97: 45403 | B97: West | C97: Printer | D97: 17 | E97: 309.52 | F97: Store B | G97: Wholesale | H97: 0.05 | I97: Eva | J97: 4998.748 | K97: Online | L97: FREESHIP | M97: 0 | N97: REG100095 | O97: Cust 2539 | P97: 6.11 | Q97: 45403 | R97: 45409 | S97: Wendy | T97: =D97*E97 -> 5261.84 | U97: =T97*H97 -> 263.092 | V97: =T97-U97 -> 4998.748 | W97: =R97-Q97 -> 6 | X97: =V97-(E97*D97) -> -263.092 | Y97: =IF(M97 = "Yes", -V97,0) -> 0
A98: 45688 | B98: Central | C98: Monitor | D98: 1 | E98: 323.83 | F98: Store B | G98: Wholesale | H98: 0.05 | I98: Eva | J98: 307.6385 | K98: Credit Card | L98: WINTER15 | M98: 0 | N98: REG100096 | O98: Cust 3916 | P98: 27.48 | Q98: 45688 | R98: 45696 | S98: Cameron | T98: =D98*E98 -> 323.83 | U98: =T98*H98 -> 16.1915 | V98: =T98-U98 -> 307.6385 | W98: =R98-Q98 -> 8 | X98: =V98-(E98*D98) -> -16.1915 | Y98: =IF(M98 = "Yes", -V98,0) -> 0
A99: 45730 | B99: Central | C99: Chair | D99: 10 | E99: 503.07 | F99: Store C | G99: Retail | H99: 0 | I99: Bob | J99: 5030.7 | K99: Credit Card | L99: FREESHIP | M99: 0 | N99: REG100097 | O99: Cust 6329 | P99: 44.61 | Q99: 45730 | R99: 45735 | S99: Cameron | T99: =D99*E99 -> 5030.7 | U99: =T99*H99 -> 0 | V99: =T99-U99 -> 5030.7 | W99: =R99-Q99 -> 5 | X99: =V99-(E99*D99) -> 0 | Y99: =IF(M99 = "Yes", -V99,0) -> 0
A100: 45438 | B100: West | C100: Laptop | D100: 20 | E100: 491.68 | F100: Store D | G100: Wholesale | H100: 0.15 | I100: Alice | J100: 8358.56 | K100: Online | L100: SAVE10 | M100: 1 | N100: REG100098 | O100: Cust 4384 | P100: 43.46 | Q100: 45438 | R100: 45441 | S100: Wendy | T100: =D100*E100 -> 9833.6 | U100: =T100*H100 -> 1475.04 | V100: =T100-U100 -> 8358.56 | W100: =R100-Q100 -> 3 | X100: =V100-(E100*D100) -> -1475.04 | Y100: =IF(M100 = "Yes", -V100,0) -> 0
...
